<annotation>
	<folder>JPEGImages</folder>
	<filename>train_0694_000000040924.jpg</filename>
	<source>
	<database>Source</database>
	</source>
	<size>
		<width>600</width>
		<height>393</height>
		<depth>3</depth>
	</size>
	<segmented>0</segmented>
	<object>
		<name>hand</name>
		<pose>Unspecified</pose>
		<truncated>0</truncated>
		<difficult>0</difficult>
		<bndbox>
			<xmin>145</xmin>
			<xmax>190</xmax>
			<ymin>123</ymin>
			<ymax>160</ymax>
		</bndbox>
		<contact_state>1,0,0,0,</contact_state>
		<hand_id>1</hand_id>
	</object>

	<object>
		<name>hand</name>
		<pose>Unspecified</pose>
		<truncated>0</truncated>
		<difficult>0</difficult>
		<bndbox>
			<xmin>332</xmin>
			<xmax>364</xmax>
			<ymin>160</ymin>
			<ymax>206</ymax>
		</bndbox>
		<contact_state>0,0,0,1,</contact_state>
		<hand_id>2</hand_id>
	</object>

	<object>
		<name>hand</name>
		<pose>Unspecified</pose>
		<truncated>0</truncated>
		<difficult>0</difficult>
		<bndbox>
			<xmin>268</xmin>
			<xmax>314</xmax>
			<ymin>54</ymin>
			<ymax>93</ymax>
		</bndbox>
		<contact_state>0,0,0,1,</contact_state>
		<hand_id>3</hand_id>
	</object>

	<object>
		<name>hand</name>
		<pose>Unspecified</pose>
		<truncated>0</truncated>
		<difficult>0</difficult>
		<bndbox>
			<xmin>441</xmin>
			<xmax>486</xmax>
			<ymin>106</ymin>
			<ymax>164</ymax>
		</bndbox>
		<contact_state>0,1,0,0,</contact_state>
		<hand_id>4</hand_id>
	</object>

	<object>
		<name>hand</name>
		<pose>Unspecified</pose>
		<truncated>0</truncated>
		<difficult>0</difficult>
		<bndbox>
			<xmin>63</xmin>
			<xmax>122</xmax>
			<ymin>142</ymin>
			<ymax>259</ymax>
		</bndbox>
		<contact_state>0,1,0,0,</contact_state>
		<hand_id>5</hand_id>
	</object>

	<object>
		<name>hand</name>
		<pose>Unspecified</pose>
		<truncated>0</truncated>
		<difficult>0</difficult>
		<bndbox>
			<xmin>141</xmin>
			<xmax>174</xmax>
			<ymin>70</ymin>
			<ymax>113</ymax>
		</bndbox>
		<contact_state>0,1,0,0,</contact_state>
		<hand_id>6</hand_id>
	</object>

	<object>
		<name>hand</name>
		<pose>Unspecified</pose>
		<truncated>0</truncated>
		<difficult>0</difficult>
		<bndbox>
			<xmin>324</xmin>
			<xmax>336</xmax>
			<ymin>140</ymin>
			<ymax>152</ymax>
		</bndbox>
		<contact_state>0,0,0,1,</contact_state>
		<hand_id>7</hand_id>
	</object>

	<object>
		<name>hand</name>
		<pose>Unspecified</pose>
		<truncated>0</truncated>
		<difficult>0</difficult>
		<bndbox>
			<xmin>348</xmin>
			<xmax>364</xmax>
			<ymin>92</ymin>
			<ymax>122</ymax>
		</bndbox>
		<contact_state>0,0,0,1,</contact_state>
		<hand_id>8</hand_id>
	</object>
</annotation>