<annotation>
	<folder>JPEGImages</folder>
	<filename>train_3206_Buffy_341.jpg</filename>
	<source>
	<database>Source</database>
	</source>
	<size>
		<width>668</width>
		<height>698</height>
		<depth>3</depth>
	</size>
	<segmented>0</segmented>
	<object>
		<name>hand</name>
		<pose>Unspecified</pose>
		<truncated>0</truncated>
		<difficult>0</difficult>
		<bndbox>
			<xmin>369</xmin>
			<xmax>420</xmax>
			<ymin>458</ymin>
			<ymax>490</ymax>
		</bndbox>
		<contact_state>0,1,0,0,</contact_state>
		<hand_id>1</hand_id>
	</object>

	<object>
		<name>hand</name>
		<pose>Unspecified</pose>
		<truncated>0</truncated>
		<difficult>0</difficult>
		<bndbox>
			<xmin>430</xmin>
			<xmax>442</xmax>
			<ymin>314</ymin>
			<ymax>340</ymax>
		</bndbox>
		<contact_state>1,0,0,0,</contact_state>
		<hand_id>2</hand_id>
	</object>

	<object>
		<name>hand</name>
		<pose>Unspecified</pose>
		<truncated>0</truncated>
		<difficult>0</difficult>
		<bndbox>
			<xmin>510</xmin>
			<xmax>529</xmax>
			<ymin>263</ymin>
			<ymax>286</ymax>
		</bndbox>
		<contact_state>0,0,1,0,</contact_state>
		<hand_id>3</hand_id>
	</object>

	<object>
		<name>hand</name>
		<pose>Unspecified</pose>
		<truncated>0</truncated>
		<difficult>0</difficult>
		<bndbox>
			<xmin>272</xmin>
			<xmax>291</xmax>
			<ymin>460</ymin>
			<ymax>487</ymax>
		</bndbox>
		<contact_state>0,1,0,0,</contact_state>
		<hand_id>4</hand_id>
	</object>
</annotation>