<annotation>
	<folder>JPEGImages</folder>
	<filename>train_3624_Movie_apollo13_2.jpg</filename>
	<source>
	<database>Source</database>
	</source>
	<size>
		<width>720</width>
		<height>390</height>
		<depth>3</depth>
	</size>
	<segmented>0</segmented>
	<object>
		<name>hand</name>
		<pose>Unspecified</pose>
		<truncated>0</truncated>
		<difficult>0</difficult>
		<bndbox>
			<xmin>116</xmin>
			<xmax>155</xmax>
			<ymin>177</ymin>
			<ymax>205</ymax>
		</bndbox>
		<contact_state>0,0,0,1,</contact_state>
		<hand_id>1</hand_id>
	</object>

	<object>
		<name>hand</name>
		<pose>Unspecified</pose>
		<truncated>0</truncated>
		<difficult>0</difficult>
		<bndbox>
			<xmin>178</xmin>
			<xmax>217</xmax>
			<ymin>184</ymin>
			<ymax>206</ymax>
		</bndbox>
		<contact_state>0,0,0,1,</contact_state>
		<hand_id>2</hand_id>
	</object>

	<object>
		<name>hand</name>
		<pose>Unspecified</pose>
		<truncated>0</truncated>
		<difficult>0</difficult>
		<bndbox>
			<xmin>21</xmin>
			<xmax>72</xmax>
			<ymin>291</ymin>
			<ymax>321</ymax>
		</bndbox>
		<contact_state>0,0,0,1,</contact_state>
		<hand_id>3</hand_id>
	</object>

	<object>
		<name>hand</name>
		<pose>Unspecified</pose>
		<truncated>0</truncated>
		<difficult>0</difficult>
		<bndbox>
			<xmin>412</xmin>
			<xmax>446</xmax>
			<ymin>189</ymin>
			<ymax>234</ymax>
		</bndbox>
		<contact_state>0,0,0,1,</contact_state>
		<hand_id>4</hand_id>
	</object>

	<object>
		<name>hand</name>
		<pose>Unspecified</pose>
		<truncated>0</truncated>
		<difficult>0</difficult>
		<bndbox>
			<xmin>575</xmin>
			<xmax>606</xmax>
			<ymin>231</ymin>
			<ymax>254</ymax>
		</bndbox>
		<contact_state>0,0,0,1,</contact_state>
		<hand_id>5</hand_id>
	</object>

	<object>
		<name>hand</name>
		<pose>Unspecified</pose>
		<truncated>0</truncated>
		<difficult>0</difficult>
		<bndbox>
			<xmin>95</xmin>
			<xmax>123</xmax>
			<ymin>186</ymin>
			<ymax>204</ymax>
		</bndbox>
		<contact_state>0,0,0,1,</contact_state>
		<hand_id>6</hand_id>
	</object>
</annotation>