<annotation>
	<folder>JPEGImages</folder>
	<filename>train_3190_Buffy_194.jpg</filename>
	<source>
	<database>Source</database>
	</source>
	<size>
		<width>535</width>
		<height>597</height>
		<depth>3</depth>
	</size>
	<segmented>0</segmented>
	<object>
		<name>hand</name>
		<pose>Unspecified</pose>
		<truncated>0</truncated>
		<difficult>0</difficult>
		<bndbox>
			<xmin>295</xmin>
			<xmax>347</xmax>
			<ymin>358</ymin>
			<ymax>415</ymax>
		</bndbox>
		<contact_state>1,0,0,0,</contact_state>
		<hand_id>1</hand_id>
	</object>

	<object>
		<name>hand</name>
		<pose>Unspecified</pose>
		<truncated>0</truncated>
		<difficult>0</difficult>
		<bndbox>
			<xmin>188</xmin>
			<xmax>243</xmax>
			<ymin>334</ymin>
			<ymax>389</ymax>
		</bndbox>
		<contact_state>0,0,0,1,</contact_state>
		<hand_id>2</hand_id>
	</object>

	<object>
		<name>hand</name>
		<pose>Unspecified</pose>
		<truncated>0</truncated>
		<difficult>0</difficult>
		<bndbox>
			<xmin>386</xmin>
			<xmax>421</xmax>
			<ymin>378</ymin>
			<ymax>399</ymax>
		</bndbox>
		<contact_state>1,0,0,0,</contact_state>
		<hand_id>3</hand_id>
	</object>
</annotation>