<annotation>
	<folder>JPEGImages</folder>
	<filename>train_3173_VOC2010_57.jpg</filename>
	<source>
	<database>Source</database>
	</source>
	<size>
		<width>500</width>
		<height>294</height>
		<depth>3</depth>
	</size>
	<segmented>0</segmented>
	<object>
		<name>hand</name>
		<pose>Unspecified</pose>
		<truncated>0</truncated>
		<difficult>0</difficult>
		<bndbox>
			<xmin>233</xmin>
			<xmax>275</xmax>
			<ymin>75</ymin>
			<ymax>129</ymax>
		</bndbox>
		<contact_state>1,0,0,0,</contact_state>
		<hand_id>1</hand_id>
	</object>

	<object>
		<name>hand</name>
		<pose>Unspecified</pose>
		<truncated>0</truncated>
		<difficult>0</difficult>
		<bndbox>
			<xmin>253</xmin>
			<xmax>295</xmax>
			<ymin>116</ymin>
			<ymax>152</ymax>
		</bndbox>
		<contact_state>0,0,1,0,</contact_state>
		<hand_id>2</hand_id>
	</object>

	<object>
		<name>hand</name>
		<pose>Unspecified</pose>
		<truncated>0</truncated>
		<difficult>0</difficult>
		<bndbox>
			<xmin>285</xmin>
			<xmax>342</xmax>
			<ymin>78</ymin>
			<ymax>114</ymax>
		</bndbox>
		<contact_state>0,0,1,0,</contact_state>
		<hand_id>3</hand_id>
	</object>

	<object>
		<name>hand</name>
		<pose>Unspecified</pose>
		<truncated>0</truncated>
		<difficult>0</difficult>
		<bndbox>
			<xmin>190</xmin>
			<xmax>234</xmax>
			<ymin>67</ymin>
			<ymax>95</ymax>
		</bndbox>
		<contact_state>1,0,0,0,</contact_state>
		<hand_id>4</hand_id>
	</object>

	<object>
		<name>hand</name>
		<pose>Unspecified</pose>
		<truncated>0</truncated>
		<difficult>0</difficult>
		<bndbox>
			<xmin>161</xmin>
			<xmax>190</xmax>
			<ymin>237</ymin>
			<ymax>262</ymax>
		</bndbox>
		<contact_state>0,0,0,1,</contact_state>
		<hand_id>5</hand_id>
	</object>

	<object>
		<name>hand</name>
		<pose>Unspecified</pose>
		<truncated>0</truncated>
		<difficult>0</difficult>
		<bndbox>
			<xmin>274</xmin>
			<xmax>299</xmax>
			<ymin>243</ymin>
			<ymax>265</ymax>
		</bndbox>
		<contact_state>1,0,0,0,</contact_state>
		<hand_id>6</hand_id>
	</object>
</annotation>