<annotation>
	<folder>JPEGImages</folder>
	<filename>train_3428_VOC2007_709.jpg</filename>
	<source>
	<database>Source</database>
	</source>
	<size>
		<width>500</width>
		<height>364</height>
		<depth>3</depth>
	</size>
	<segmented>0</segmented>
	<object>
		<name>hand</name>
		<pose>Unspecified</pose>
		<truncated>0</truncated>
		<difficult>0</difficult>
		<bndbox>
			<xmin>17</xmin>
			<xmax>47</xmax>
			<ymin>308</ymin>
			<ymax>330</ymax>
		</bndbox>
		<contact_state>0,0,0,1,</contact_state>
		<hand_id>1</hand_id>
	</object>

	<object>
		<name>hand</name>
		<pose>Unspecified</pose>
		<truncated>0</truncated>
		<difficult>0</difficult>
		<bndbox>
			<xmin>227</xmin>
			<xmax>260</xmax>
			<ymin>151</ymin>
			<ymax>198</ymax>
		</bndbox>
		<contact_state>0,0,0,1,</contact_state>
		<hand_id>2</hand_id>
	</object>

	<object>
		<name>hand</name>
		<pose>Unspecified</pose>
		<truncated>0</truncated>
		<difficult>0</difficult>
		<bndbox>
			<xmin>225</xmin>
			<xmax>262</xmax>
			<ymin>55</ymin>
			<ymax>101</ymax>
		</bndbox>
		<contact_state>0,0,0,1,</contact_state>
		<hand_id>3</hand_id>
	</object>

	<object>
		<name>hand</name>
		<pose>Unspecified</pose>
		<truncated>0</truncated>
		<difficult>0</difficult>
		<bndbox>
			<xmin>415</xmin>
			<xmax>448</xmax>
			<ymin>186</ymin>
			<ymax>231</ymax>
		</bndbox>
		<contact_state>0,0,0,1,</contact_state>
		<hand_id>4</hand_id>
	</object>

	<object>
		<name>hand</name>
		<pose>Unspecified</pose>
		<truncated>0</truncated>
		<difficult>0</difficult>
		<bndbox>
			<xmin>69</xmin>
			<xmax>97</xmax>
			<ymin>280</ymin>
			<ymax>313</ymax>
		</bndbox>
		<contact_state>0,0,0,1,</contact_state>
		<hand_id>5</hand_id>
	</object>

	<object>
		<name>hand</name>
		<pose>Unspecified</pose>
		<truncated>0</truncated>
		<difficult>0</difficult>
		<bndbox>
			<xmin>147</xmin>
			<xmax>181</xmax>
			<ymin>174</ymin>
			<ymax>207</ymax>
		</bndbox>
		<contact_state>0,0,0,1,</contact_state>
		<hand_id>6</hand_id>
	</object>
</annotation>