<annotation>
	<folder>JPEGImages</folder>
	<filename>train_3795_dancing_00174.jpg</filename>
	<source>
	<database>Source</database>
	</source>
	<size>
		<width>600</width>
		<height>800</height>
		<depth>3</depth>
	</size>
	<segmented>0</segmented>
	<object>
		<name>hand</name>
		<pose>Unspecified</pose>
		<truncated>0</truncated>
		<difficult>0</difficult>
		<bndbox>
			<xmin>398</xmin>
			<xmax>452</xmax>
			<ymin>462</ymin>
			<ymax>537</ymax>
		</bndbox>
		<contact_state>1,0,0,0,</contact_state>
		<hand_id>1</hand_id>
	</object>

	<object>
		<name>hand</name>
		<pose>Unspecified</pose>
		<truncated>0</truncated>
		<difficult>0</difficult>
		<bndbox>
			<xmin>163</xmin>
			<xmax>262</xmax>
			<ymin>153</ymin>
			<ymax>209</ymax>
		</bndbox>
		<contact_state>0,1,0,0,</contact_state>
		<hand_id>2</hand_id>
	</object>

	<object>
		<name>hand</name>
		<pose>Unspecified</pose>
		<truncated>0</truncated>
		<difficult>0</difficult>
		<bndbox>
			<xmin>114</xmin>
			<xmax>151</xmax>
			<ymin>304</ymin>
			<ymax>343</ymax>
		</bndbox>
		<contact_state>0,0,1,0,</contact_state>
		<hand_id>3</hand_id>
	</object>
</annotation>