<annotation>
	<folder>JPEGImages</folder>
	<filename>train_3025_000000564447.jpg</filename>
	<source>
	<database>Source</database>
	</source>
	<size>
		<width>429</width>
		<height>640</height>
		<depth>3</depth>
	</size>
	<segmented>0</segmented>
	<object>
		<name>hand</name>
		<pose>Unspecified</pose>
		<truncated>0</truncated>
		<difficult>0</difficult>
		<bndbox>
			<xmin>318</xmin>
			<xmax>396</xmax>
			<ymin>476</ymin>
			<ymax>523</ymax>
		</bndbox>
		<contact_state>0,1,0,2,</contact_state>
		<hand_id>1</hand_id>
	</object>

	<object>
		<name>hand</name>
		<pose>Unspecified</pose>
		<truncated>0</truncated>
		<difficult>0</difficult>
		<bndbox>
			<xmin>373</xmin>
			<xmax>417</xmax>
			<ymin>440</ymin>
			<ymax>491</ymax>
		</bndbox>
		<contact_state>0,1,0,0,</contact_state>
		<hand_id>2</hand_id>
	</object>

	<object>
		<name>hand</name>
		<pose>Unspecified</pose>
		<truncated>0</truncated>
		<difficult>0</difficult>
		<bndbox>
			<xmin>233</xmin>
			<xmax>339</xmax>
			<ymin>575</ymin>
			<ymax>639</ymax>
		</bndbox>
		<contact_state>0,1,0,0,</contact_state>
		<hand_id>3</hand_id>
	</object>

	<object>
		<name>hand</name>
		<pose>Unspecified</pose>
		<truncated>0</truncated>
		<difficult>0</difficult>
		<bndbox>
			<xmin>262</xmin>
			<xmax>333</xmax>
			<ymin>560</ymin>
			<ymax>638</ymax>
		</bndbox>
		<contact_state>0,1,0,0,</contact_state>
		<hand_id>4</hand_id>
	</object>
</annotation>