<annotation>
	<folder>JPEGImages</folder>
	<filename>train_1666_000000247072.jpg</filename>
	<source>
	<database>Source</database>
	</source>
	<size>
		<width>500</width>
		<height>475</height>
		<depth>3</depth>
	</size>
	<segmented>0</segmented>
	<object>
		<name>hand</name>
		<pose>Unspecified</pose>
		<truncated>0</truncated>
		<difficult>0</difficult>
		<bndbox>
			<xmin>270</xmin>
			<xmax>302</xmax>
			<ymin>254</ymin>
			<ymax>279</ymax>
		</bndbox>
		<contact_state>1,0,0,0,</contact_state>
		<hand_id>1</hand_id>
	</object>

	<object>
		<name>hand</name>
		<pose>Unspecified</pose>
		<truncated>0</truncated>
		<difficult>0</difficult>
		<bndbox>
			<xmin>135</xmin>
			<xmax>157</xmax>
			<ymin>232</ymin>
			<ymax>252</ymax>
		</bndbox>
		<contact_state>1,0,0,0,</contact_state>
		<hand_id>2</hand_id>
	</object>

	<object>
		<name>hand</name>
		<pose>Unspecified</pose>
		<truncated>0</truncated>
		<difficult>0</difficult>
		<bndbox>
			<xmin>251</xmin>
			<xmax>270</xmax>
			<ymin>254</ymin>
			<ymax>273</ymax>
		</bndbox>
		<contact_state>1,0,0,0,</contact_state>
		<hand_id>3</hand_id>
	</object>
</annotation>