<annotation>
	<folder>JPEGImages</folder>
	<filename>train_3590_Movie_4weds_129.jpg</filename>
	<source>
	<database>Source</database>
	</source>
	<size>
		<width>720</width>
		<height>576</height>
		<depth>3</depth>
	</size>
	<segmented>0</segmented>
	<object>
		<name>hand</name>
		<pose>Unspecified</pose>
		<truncated>0</truncated>
		<difficult>0</difficult>
		<bndbox>
			<xmin>455</xmin>
			<xmax>535</xmax>
			<ymin>421</ymin>
			<ymax>480</ymax>
		</bndbox>
		<contact_state>0,1,0,0,</contact_state>
		<hand_id>1</hand_id>
	</object>

	<object>
		<name>hand</name>
		<pose>Unspecified</pose>
		<truncated>0</truncated>
		<difficult>0</difficult>
		<bndbox>
			<xmin>627</xmin>
			<xmax>672</xmax>
			<ymin>304</ymin>
			<ymax>339</ymax>
		</bndbox>
		<contact_state>1,0,0,1,</contact_state>
		<hand_id>2</hand_id>
	</object>

	<object>
		<name>hand</name>
		<pose>Unspecified</pose>
		<truncated>0</truncated>
		<difficult>0</difficult>
		<bndbox>
			<xmin>639</xmin>
			<xmax>663</xmax>
			<ymin>318</ymin>
			<ymax>352</ymax>
		</bndbox>
		<contact_state>1,0,0,0,</contact_state>
		<hand_id>3</hand_id>
	</object>
</annotation>