<annotation>
	<folder>JPEGImages</folder>
	<filename>train_3821_dancing_00697.jpg</filename>
	<source>
	<database>Source</database>
	</source>
	<size>
		<width>800</width>
		<height>531</height>
		<depth>3</depth>
	</size>
	<segmented>0</segmented>
	<object>
		<name>hand</name>
		<pose>Unspecified</pose>
		<truncated>0</truncated>
		<difficult>0</difficult>
		<bndbox>
			<xmin>337</xmin>
			<xmax>391</xmax>
			<ymin>147</ymin>
			<ymax>196</ymax>
		</bndbox>
		<contact_state>0,0,0,1,</contact_state>
		<hand_id>1</hand_id>
	</object>

	<object>
		<name>hand</name>
		<pose>Unspecified</pose>
		<truncated>0</truncated>
		<difficult>0</difficult>
		<bndbox>
			<xmin>0</xmin>
			<xmax>46</xmax>
			<ymin>193</ymin>
			<ymax>309</ymax>
		</bndbox>
		<contact_state>0,0,0,1,</contact_state>
		<hand_id>2</hand_id>
	</object>

	<object>
		<name>hand</name>
		<pose>Unspecified</pose>
		<truncated>0</truncated>
		<difficult>0</difficult>
		<bndbox>
			<xmin>413</xmin>
			<xmax>455</xmax>
			<ymin>166</ymin>
			<ymax>187</ymax>
		</bndbox>
		<contact_state>0,0,1,0,</contact_state>
		<hand_id>3</hand_id>
	</object>

	<object>
		<name>hand</name>
		<pose>Unspecified</pose>
		<truncated>0</truncated>
		<difficult>0</difficult>
		<bndbox>
			<xmin>383</xmin>
			<xmax>412</xmax>
			<ymin>265</ymin>
			<ymax>287</ymax>
		</bndbox>
		<contact_state>0,0,1,0,</contact_state>
		<hand_id>4</hand_id>
	</object>

	<object>
		<name>hand</name>
		<pose>Unspecified</pose>
		<truncated>0</truncated>
		<difficult>0</difficult>
		<bndbox>
			<xmin>569</xmin>
			<xmax>620</xmax>
			<ymin>245</ymin>
			<ymax>279</ymax>
		</bndbox>
		<contact_state>0,0,1,0,</contact_state>
		<hand_id>5</hand_id>
	</object>

	<object>
		<name>hand</name>
		<pose>Unspecified</pose>
		<truncated>0</truncated>
		<difficult>0</difficult>
		<bndbox>
			<xmin>730</xmin>
			<xmax>788</xmax>
			<ymin>139</ymin>
			<ymax>177</ymax>
		</bndbox>
		<contact_state>0,0,1,0,</contact_state>
		<hand_id>6</hand_id>
	</object>

	<object>
		<name>hand</name>
		<pose>Unspecified</pose>
		<truncated>0</truncated>
		<difficult>0</difficult>
		<bndbox>
			<xmin>747</xmin>
			<xmax>791</xmax>
			<ymin>123</ymin>
			<ymax>146</ymax>
		</bndbox>
		<contact_state>0,0,1,0,</contact_state>
		<hand_id>7</hand_id>
	</object>
</annotation>