<annotation>
	<folder>JPEGImages</folder>
	<filename>train_2513_000000443342.jpg</filename>
	<source>
	<database>Source</database>
	</source>
	<size>
		<width>640</width>
		<height>426</height>
		<depth>3</depth>
	</size>
	<segmented>0</segmented>
	<object>
		<name>hand</name>
		<pose>Unspecified</pose>
		<truncated>0</truncated>
		<difficult>0</difficult>
		<bndbox>
			<xmin>318</xmin>
			<xmax>351</xmax>
			<ymin>227</ymin>
			<ymax>271</ymax>
		</bndbox>
		<contact_state>1,0,0,0,</contact_state>
		<hand_id>1</hand_id>
	</object>

	<object>
		<name>hand</name>
		<pose>Unspecified</pose>
		<truncated>0</truncated>
		<difficult>0</difficult>
		<bndbox>
			<xmin>305</xmin>
			<xmax>339</xmax>
			<ymin>164</ymin>
			<ymax>187</ymax>
		</bndbox>
		<contact_state>1,0,0,0,</contact_state>
		<hand_id>2</hand_id>
	</object>
</annotation>