<annotation>
	<folder>JPEGImages</folder>
	<filename>train_3839_dancing_01125.jpg</filename>
	<source>
	<database>Source</database>
	</source>
	<size>
		<width>600</width>
		<height>800</height>
		<depth>3</depth>
	</size>
	<segmented>0</segmented>
	<object>
		<name>hand</name>
		<pose>Unspecified</pose>
		<truncated>0</truncated>
		<difficult>0</difficult>
		<bndbox>
			<xmin>78</xmin>
			<xmax>131</xmax>
			<ymin>472</ymin>
			<ymax>529</ymax>
		</bndbox>
		<contact_state>0,0,1,0,</contact_state>
		<hand_id>1</hand_id>
	</object>

	<object>
		<name>hand</name>
		<pose>Unspecified</pose>
		<truncated>0</truncated>
		<difficult>0</difficult>
		<bndbox>
			<xmin>551</xmin>
			<xmax>577</xmax>
			<ymin>322</ymin>
			<ymax>358</ymax>
		</bndbox>
		<contact_state>0,1,0,0,</contact_state>
		<hand_id>2</hand_id>
	</object>

	<object>
		<name>hand</name>
		<pose>Unspecified</pose>
		<truncated>0</truncated>
		<difficult>0</difficult>
		<bndbox>
			<xmin>80</xmin>
			<xmax>141</xmax>
			<ymin>458</ymin>
			<ymax>521</ymax>
		</bndbox>
		<contact_state>0,0,1,0,</contact_state>
		<hand_id>3</hand_id>
	</object>
</annotation>