<annotation>
	<folder>JPEGImages</folder>
	<filename>train_3467_VOC2010_1226.jpg</filename>
	<source>
	<database>Source</database>
	</source>
	<size>
		<width>500</width>
		<height>375</height>
		<depth>3</depth>
	</size>
	<segmented>0</segmented>
	<object>
		<name>hand</name>
		<pose>Unspecified</pose>
		<truncated>0</truncated>
		<difficult>0</difficult>
		<bndbox>
			<xmin>223</xmin>
			<xmax>249</xmax>
			<ymin>280</ymin>
			<ymax>298</ymax>
		</bndbox>
		<contact_state>0,0,0,1,</contact_state>
		<hand_id>1</hand_id>
	</object>

	<object>
		<name>hand</name>
		<pose>Unspecified</pose>
		<truncated>0</truncated>
		<difficult>0</difficult>
		<bndbox>
			<xmin>265</xmin>
			<xmax>289</xmax>
			<ymin>281</ymin>
			<ymax>301</ymax>
		</bndbox>
		<contact_state>0,1,0,1,</contact_state>
		<hand_id>2</hand_id>
	</object>

	<object>
		<name>hand</name>
		<pose>Unspecified</pose>
		<truncated>0</truncated>
		<difficult>0</difficult>
		<bndbox>
			<xmin>276</xmin>
			<xmax>303</xmax>
			<ymin>283</ymin>
			<ymax>299</ymax>
		</bndbox>
		<contact_state>0,1,0,1,</contact_state>
		<hand_id>3</hand_id>
	</object>

	<object>
		<name>hand</name>
		<pose>Unspecified</pose>
		<truncated>0</truncated>
		<difficult>0</difficult>
		<bndbox>
			<xmin>338</xmin>
			<xmax>357</xmax>
			<ymin>281</ymin>
			<ymax>312</ymax>
		</bndbox>
		<contact_state>0,0,0,1,</contact_state>
		<hand_id>4</hand_id>
	</object>

	<object>
		<name>hand</name>
		<pose>Unspecified</pose>
		<truncated>0</truncated>
		<difficult>0</difficult>
		<bndbox>
			<xmin>393</xmin>
			<xmax>414</xmax>
			<ymin>275</ymin>
			<ymax>293</ymax>
		</bndbox>
		<contact_state>0,0,0,1,</contact_state>
		<hand_id>5</hand_id>
	</object>

	<object>
		<name>hand</name>
		<pose>Unspecified</pose>
		<truncated>0</truncated>
		<difficult>0</difficult>
		<bndbox>
			<xmin>58</xmin>
			<xmax>74</xmax>
			<ymin>284</ymin>
			<ymax>299</ymax>
		</bndbox>
		<contact_state>0,0,0,1,</contact_state>
		<hand_id>6</hand_id>
	</object>
</annotation>