<annotation>
	<folder>JPEGImages</folder>
	<filename>train_0694_000000040940.jpg</filename>
	<source>
	<database>Source</database>
	</source>
	<size>
		<width>426</width>
		<height>640</height>
		<depth>3</depth>
	</size>
	<segmented>0</segmented>
	<object>
		<name>hand</name>
		<pose>Unspecified</pose>
		<truncated>0</truncated>
		<difficult>0</difficult>
		<bndbox>
			<xmin>178</xmin>
			<xmax>223</xmax>
			<ymin>332</ymin>
			<ymax>376</ymax>
		</bndbox>
		<contact_state>0,1,0,1,</contact_state>
		<hand_id>1</hand_id>
	</object>

	<object>
		<name>hand</name>
		<pose>Unspecified</pose>
		<truncated>0</truncated>
		<difficult>0</difficult>
		<bndbox>
			<xmin>204</xmin>
			<xmax>266</xmax>
			<ymin>335</ymin>
			<ymax>381</ymax>
		</bndbox>
		<contact_state>0,1,0,1,</contact_state>
		<hand_id>2</hand_id>
	</object>

	<object>
		<name>hand</name>
		<pose>Unspecified</pose>
		<truncated>0</truncated>
		<difficult>0</difficult>
		<bndbox>
			<xmin>196</xmin>
			<xmax>223</xmax>
			<ymin>456</ymin>
			<ymax>477</ymax>
		</bndbox>
		<contact_state>0,0,0,1,</contact_state>
		<hand_id>3</hand_id>
	</object>

	<object>
		<name>hand</name>
		<pose>Unspecified</pose>
		<truncated>0</truncated>
		<difficult>0</difficult>
		<bndbox>
			<xmin>233</xmin>
			<xmax>266</xmax>
			<ymin>444</ymin>
			<ymax>478</ymax>
		</bndbox>
		<contact_state>0,0,0,1,</contact_state>
		<hand_id>4</hand_id>
	</object>

	<object>
		<name>hand</name>
		<pose>Unspecified</pose>
		<truncated>0</truncated>
		<difficult>0</difficult>
		<bndbox>
			<xmin>79</xmin>
			<xmax>98</xmax>
			<ymin>424</ymin>
			<ymax>440</ymax>
		</bndbox>
		<contact_state>0,0,0,1,</contact_state>
		<hand_id>5</hand_id>
	</object>
</annotation>