<annotation>
	<folder>JPEGImages</folder>
	<filename>train_0103_013349_003.jpg</filename>
	<source>
	<database>Source</database>
	</source>
	<size>
		<width>640</width>
		<height>360</height>
		<depth>3</depth>
	</size>
	<segmented>0</segmented>
	<object>
		<name>hand</name>
		<pose>Unspecified</pose>
		<truncated>0</truncated>
		<difficult>0</difficult>
		<bndbox>
			<xmin>238</xmin>
			<xmax>316</xmax>
			<ymin>302</ymin>
			<ymax>340</ymax>
		</bndbox>
		<contact_state>0,0,0,1,</contact_state>
		<hand_id>1</hand_id>
	</object>

	<object>
		<name>hand</name>
		<pose>Unspecified</pose>
		<truncated>0</truncated>
		<difficult>0</difficult>
		<bndbox>
			<xmin>324</xmin>
			<xmax>390</xmax>
			<ymin>317</ymin>
			<ymax>359</ymax>
		</bndbox>
		<contact_state>0,0,0,1,</contact_state>
		<hand_id>2</hand_id>
	</object>

	<object>
		<name>hand</name>
		<pose>Unspecified</pose>
		<truncated>0</truncated>
		<difficult>0</difficult>
		<bndbox>
			<xmin>115</xmin>
			<xmax>155</xmax>
			<ymin>311</ymin>
			<ymax>329</ymax>
		</bndbox>
		<contact_state>0,0,0,1,</contact_state>
		<hand_id>3</hand_id>
	</object>
</annotation>