<annotation>
	<folder>JPEGImages</folder>
	<filename>train_3941_friends_00461.jpg</filename>
	<source>
	<database>Source</database>
	</source>
	<size>
		<width>800</width>
		<height>590</height>
		<depth>3</depth>
	</size>
	<segmented>0</segmented>
	<object>
		<name>hand</name>
		<pose>Unspecified</pose>
		<truncated>0</truncated>
		<difficult>0</difficult>
		<bndbox>
			<xmin>152</xmin>
			<xmax>277</xmax>
			<ymin>361</ymin>
			<ymax>446</ymax>
		</bndbox>
		<contact_state>1,0,0,0,</contact_state>
		<hand_id>1</hand_id>
	</object>

	<object>
		<name>hand</name>
		<pose>Unspecified</pose>
		<truncated>0</truncated>
		<difficult>0</difficult>
		<bndbox>
			<xmin>699</xmin>
			<xmax>750</xmax>
			<ymin>231</ymin>
			<ymax>300</ymax>
		</bndbox>
		<contact_state>0,0,1,1,</contact_state>
		<hand_id>2</hand_id>
	</object>

	<object>
		<name>hand</name>
		<pose>Unspecified</pose>
		<truncated>0</truncated>
		<difficult>0</difficult>
		<bndbox>
			<xmin>290</xmin>
			<xmax>350</xmax>
			<ymin>271</ymin>
			<ymax>350</ymax>
		</bndbox>
		<contact_state>1,0,0,0,</contact_state>
		<hand_id>3</hand_id>
	</object>

	<object>
		<name>hand</name>
		<pose>Unspecified</pose>
		<truncated>0</truncated>
		<difficult>0</difficult>
		<bndbox>
			<xmin>406</xmin>
			<xmax>449</xmax>
			<ymin>189</ymin>
			<ymax>235</ymax>
		</bndbox>
		<contact_state>0,0,1,0,</contact_state>
		<hand_id>4</hand_id>
	</object>

	<object>
		<name>hand</name>
		<pose>Unspecified</pose>
		<truncated>0</truncated>
		<difficult>0</difficult>
		<bndbox>
			<xmin>598</xmin>
			<xmax>723</xmax>
			<ymin>302</ymin>
			<ymax>390</ymax>
		</bndbox>
		<contact_state>1,0,0,0,</contact_state>
		<hand_id>5</hand_id>
	</object>

	<object>
		<name>hand</name>
		<pose>Unspecified</pose>
		<truncated>0</truncated>
		<difficult>0</difficult>
		<bndbox>
			<xmin>2</xmin>
			<xmax>75</xmax>
			<ymin>139</ymin>
			<ymax>207</ymax>
		</bndbox>
		<contact_state>1,0,0,0,</contact_state>
		<hand_id>6</hand_id>
	</object>

	<object>
		<name>hand</name>
		<pose>Unspecified</pose>
		<truncated>0</truncated>
		<difficult>0</difficult>
		<bndbox>
			<xmin>480</xmin>
			<xmax>550</xmax>
			<ymin>403</ymin>
			<ymax>504</ymax>
		</bndbox>
		<contact_state>1,0,0,0,</contact_state>
		<hand_id>7</hand_id>
	</object>

	<object>
		<name>hand</name>
		<pose>Unspecified</pose>
		<truncated>0</truncated>
		<difficult>0</difficult>
		<bndbox>
			<xmin>313</xmin>
			<xmax>369</xmax>
			<ymin>240</ymin>
			<ymax>291</ymax>
		</bndbox>
		<contact_state>0,0,1,0,</contact_state>
		<hand_id>8</hand_id>
	</object>

	<object>
		<name>hand</name>
		<pose>Unspecified</pose>
		<truncated>0</truncated>
		<difficult>0</difficult>
		<bndbox>
			<xmin>225</xmin>
			<xmax>299</xmax>
			<ymin>391</ymin>
			<ymax>451</ymax>
		</bndbox>
		<contact_state>0,0,1,0,</contact_state>
		<hand_id>9</hand_id>
	</object>
</annotation>