<annotation>
	<folder>JPEGImages</folder>
	<filename>train_1357_000000173631.jpg</filename>
	<source>
	<database>Source</database>
	</source>
	<size>
		<width>423</width>
		<height>640</height>
		<depth>3</depth>
	</size>
	<segmented>0</segmented>
	<object>
		<name>hand</name>
		<pose>Unspecified</pose>
		<truncated>0</truncated>
		<difficult>0</difficult>
		<bndbox>
			<xmin>61</xmin>
			<xmax>84</xmax>
			<ymin>280</ymin>
			<ymax>312</ymax>
		</bndbox>
		<contact_state>1,0,0,0,</contact_state>
		<hand_id>1</hand_id>
	</object>

	<object>
		<name>hand</name>
		<pose>Unspecified</pose>
		<truncated>0</truncated>
		<difficult>0</difficult>
		<bndbox>
			<xmin>148</xmin>
			<xmax>191</xmax>
			<ymin>290</ymin>
			<ymax>336</ymax>
		</bndbox>
		<contact_state>0,0,1,0,</contact_state>
		<hand_id>2</hand_id>
	</object>

	<object>
		<name>hand</name>
		<pose>Unspecified</pose>
		<truncated>0</truncated>
		<difficult>0</difficult>
		<bndbox>
			<xmin>247</xmin>
			<xmax>312</xmax>
			<ymin>330</ymin>
			<ymax>376</ymax>
		</bndbox>
		<contact_state>0,0,1,0,</contact_state>
		<hand_id>3</hand_id>
	</object>

	<object>
		<name>hand</name>
		<pose>Unspecified</pose>
		<truncated>0</truncated>
		<difficult>0</difficult>
		<bndbox>
			<xmin>102</xmin>
			<xmax>114</xmax>
			<ymin>355</ymin>
			<ymax>378</ymax>
		</bndbox>
		<contact_state>1,0,0,0,</contact_state>
		<hand_id>4</hand_id>
	</object>

	<object>
		<name>hand</name>
		<pose>Unspecified</pose>
		<truncated>0</truncated>
		<difficult>0</difficult>
		<bndbox>
			<xmin>295</xmin>
			<xmax>323</xmax>
			<ymin>399</ymin>
			<ymax>450</ymax>
		</bndbox>
		<contact_state>1,0,0,0,</contact_state>
		<hand_id>5</hand_id>
	</object>
</annotation>