<annotation>
	<folder>JPEGImages</folder>
	<filename>train_2503_000000441240.jpg</filename>
	<source>
	<database>Source</database>
	</source>
	<size>
		<width>640</width>
		<height>480</height>
		<depth>3</depth>
	</size>
	<segmented>0</segmented>
	<object>
		<name>hand</name>
		<pose>Unspecified</pose>
		<truncated>0</truncated>
		<difficult>0</difficult>
		<bndbox>
			<xmin>287</xmin>
			<xmax>314</xmax>
			<ymin>235</ymin>
			<ymax>268</ymax>
		</bndbox>
		<contact_state>1,0,0,0,</contact_state>
		<hand_id>1</hand_id>
	</object>

	<object>
		<name>hand</name>
		<pose>Unspecified</pose>
		<truncated>0</truncated>
		<difficult>0</difficult>
		<bndbox>
			<xmin>397</xmin>
			<xmax>423</xmax>
			<ymin>260</ymin>
			<ymax>277</ymax>
		</bndbox>
		<contact_state>0,0,0,1,</contact_state>
		<hand_id>2</hand_id>
	</object>

	<object>
		<name>hand</name>
		<pose>Unspecified</pose>
		<truncated>0</truncated>
		<difficult>0</difficult>
		<bndbox>
			<xmin>229</xmin>
			<xmax>253</xmax>
			<ymin>351</ymin>
			<ymax>382</ymax>
		</bndbox>
		<contact_state>1,0,0,0,</contact_state>
		<hand_id>3</hand_id>
	</object>

	<object>
		<name>hand</name>
		<pose>Unspecified</pose>
		<truncated>0</truncated>
		<difficult>0</difficult>
		<bndbox>
			<xmin>332</xmin>
			<xmax>354</xmax>
			<ymin>244</ymin>
			<ymax>272</ymax>
		</bndbox>
		<contact_state>0,0,0,1,</contact_state>
		<hand_id>4</hand_id>
	</object>
</annotation>