<annotation>
	<folder>JPEGImages</folder>
	<filename>train_0027_004035_004.jpg</filename>
	<source>
	<database>Source</database>
	</source>
	<size>
		<width>480</width>
		<height>360</height>
		<depth>3</depth>
	</size>
	<segmented>0</segmented>
	<object>
		<name>hand</name>
		<pose>Unspecified</pose>
		<truncated>0</truncated>
		<difficult>0</difficult>
		<bndbox>
			<xmin>156</xmin>
			<xmax>248</xmax>
			<ymin>317</ymin>
			<ymax>359</ymax>
		</bndbox>
		<contact_state>0,1,0,0,</contact_state>
		<hand_id>1</hand_id>
	</object>

	<object>
		<name>hand</name>
		<pose>Unspecified</pose>
		<truncated>0</truncated>
		<difficult>0</difficult>
		<bndbox>
			<xmin>387</xmin>
			<xmax>427</xmax>
			<ymin>157</ymin>
			<ymax>248</ymax>
		</bndbox>
		<contact_state>0,0,1,0,</contact_state>
		<hand_id>2</hand_id>
	</object>

	<object>
		<name>hand</name>
		<pose>Unspecified</pose>
		<truncated>0</truncated>
		<difficult>0</difficult>
		<bndbox>
			<xmin>138</xmin>
			<xmax>204</xmax>
			<ymin>300</ymin>
			<ymax>326</ymax>
		</bndbox>
		<contact_state>0,1,0,0,</contact_state>
		<hand_id>3</hand_id>
	</object>

	<object>
		<name>hand</name>
		<pose>Unspecified</pose>
		<truncated>0</truncated>
		<difficult>0</difficult>
		<bndbox>
			<xmin>146</xmin>
			<xmax>202</xmax>
			<ymin>266</ymin>
			<ymax>319</ymax>
		</bndbox>
		<contact_state>0,0,1,0,</contact_state>
		<hand_id>4</hand_id>
	</object>
</annotation>