<annotation>
	<folder>JPEGImages</folder>
	<filename>train_2698_000000486125.jpg</filename>
	<source>
	<database>Source</database>
	</source>
	<size>
		<width>640</width>
		<height>425</height>
		<depth>3</depth>
	</size>
	<segmented>0</segmented>
	<object>
		<name>hand</name>
		<pose>Unspecified</pose>
		<truncated>0</truncated>
		<difficult>0</difficult>
		<bndbox>
			<xmin>88</xmin>
			<xmax>158</xmax>
			<ymin>182</ymin>
			<ymax>243</ymax>
		</bndbox>
		<contact_state>0,1,0,1,</contact_state>
		<hand_id>1</hand_id>
	</object>

	<object>
		<name>hand</name>
		<pose>Unspecified</pose>
		<truncated>0</truncated>
		<difficult>0</difficult>
		<bndbox>
			<xmin>136</xmin>
			<xmax>217</xmax>
			<ymin>192</ymin>
			<ymax>257</ymax>
		</bndbox>
		<contact_state>0,1,0,1,</contact_state>
		<hand_id>2</hand_id>
	</object>
</annotation>