<annotation>
	<folder>JPEGImages</folder>
	<filename>train_2901_000000535308.jpg</filename>
	<source>
	<database>Source</database>
	</source>
	<size>
		<width>640</width>
		<height>393</height>
		<depth>3</depth>
	</size>
	<segmented>0</segmented>
	<object>
		<name>hand</name>
		<pose>Unspecified</pose>
		<truncated>0</truncated>
		<difficult>0</difficult>
		<bndbox>
			<xmin>198</xmin>
			<xmax>220</xmax>
			<ymin>165</ymin>
			<ymax>176</ymax>
		</bndbox>
		<contact_state>1,0,0,0,</contact_state>
		<hand_id>1</hand_id>
	</object>

	<object>
		<name>hand</name>
		<pose>Unspecified</pose>
		<truncated>0</truncated>
		<difficult>0</difficult>
		<bndbox>
			<xmin>226</xmin>
			<xmax>243</xmax>
			<ymin>90</ymin>
			<ymax>103</ymax>
		</bndbox>
		<contact_state>1,0,0,0,</contact_state>
		<hand_id>2</hand_id>
	</object>
</annotation>