<annotation>
	<folder>JPEGImages</folder>
	<filename>train_3453_VOC2010_1094.jpg</filename>
	<source>
	<database>Source</database>
	</source>
	<size>
		<width>500</width>
		<height>335</height>
		<depth>3</depth>
	</size>
	<segmented>0</segmented>
	<object>
		<name>hand</name>
		<pose>Unspecified</pose>
		<truncated>0</truncated>
		<difficult>0</difficult>
		<bndbox>
			<xmin>196</xmin>
			<xmax>229</xmax>
			<ymin>69</ymin>
			<ymax>90</ymax>
		</bndbox>
		<contact_state>0,0,0,1,</contact_state>
		<hand_id>1</hand_id>
	</object>

	<object>
		<name>hand</name>
		<pose>Unspecified</pose>
		<truncated>0</truncated>
		<difficult>0</difficult>
		<bndbox>
			<xmin>281</xmin>
			<xmax>306</xmax>
			<ymin>52</ymin>
			<ymax>75</ymax>
		</bndbox>
		<contact_state>0,1,0,0,</contact_state>
		<hand_id>2</hand_id>
	</object>
</annotation>