<annotation>
	<folder>JPEGImages</folder>
	<filename>train_3307_Poselet_242.jpg</filename>
	<source>
	<database>Source</database>
	</source>
	<size>
		<width>1024</width>
		<height>768</height>
		<depth>3</depth>
	</size>
	<segmented>0</segmented>
	<object>
		<name>hand</name>
		<pose>Unspecified</pose>
		<truncated>0</truncated>
		<difficult>0</difficult>
		<bndbox>
			<xmin>505</xmin>
			<xmax>615</xmax>
			<ymin>428</ymin>
			<ymax>503</ymax>
		</bndbox>
		<contact_state>0,0,0,1,</contact_state>
		<hand_id>1</hand_id>
	</object>

	<object>
		<name>hand</name>
		<pose>Unspecified</pose>
		<truncated>0</truncated>
		<difficult>0</difficult>
		<bndbox>
			<xmin>564</xmin>
			<xmax>591</xmax>
			<ymin>326</ymin>
			<ymax>353</ymax>
		</bndbox>
		<contact_state>0,0,0,1,</contact_state>
		<hand_id>2</hand_id>
	</object>
</annotation>