<annotation>
	<folder>JPEGImages</folder>
	<filename>train_4162_seminar_00154.jpg</filename>
	<source>
	<database>Source</database>
	</source>
	<size>
		<width>800</width>
		<height>600</height>
		<depth>3</depth>
	</size>
	<segmented>0</segmented>
	<object>
		<name>hand</name>
		<pose>Unspecified</pose>
		<truncated>0</truncated>
		<difficult>0</difficult>
		<bndbox>
			<xmin>12</xmin>
			<xmax>59</xmax>
			<ymin>504</ymin>
			<ymax>538</ymax>
		</bndbox>
		<contact_state>0,1,0,0,</contact_state>
		<hand_id>1</hand_id>
	</object>

	<object>
		<name>hand</name>
		<pose>Unspecified</pose>
		<truncated>0</truncated>
		<difficult>0</difficult>
		<bndbox>
			<xmin>308</xmin>
			<xmax>336</xmax>
			<ymin>347</ymin>
			<ymax>364</ymax>
		</bndbox>
		<contact_state>0,0,0,1,</contact_state>
		<hand_id>2</hand_id>
	</object>

	<object>
		<name>hand</name>
		<pose>Unspecified</pose>
		<truncated>0</truncated>
		<difficult>0</difficult>
		<bndbox>
			<xmin>315</xmin>
			<xmax>336</xmax>
			<ymin>328</ymin>
			<ymax>341</ymax>
		</bndbox>
		<contact_state>0,0,0,1,</contact_state>
		<hand_id>3</hand_id>
	</object>

	<object>
		<name>hand</name>
		<pose>Unspecified</pose>
		<truncated>0</truncated>
		<difficult>0</difficult>
		<bndbox>
			<xmin>508</xmin>
			<xmax>533</xmax>
			<ymin>321</ymin>
			<ymax>335</ymax>
		</bndbox>
		<contact_state>0,0,0,1,</contact_state>
		<hand_id>4</hand_id>
	</object>

	<object>
		<name>hand</name>
		<pose>Unspecified</pose>
		<truncated>0</truncated>
		<difficult>0</difficult>
		<bndbox>
			<xmin>547</xmin>
			<xmax>581</xmax>
			<ymin>465</ymin>
			<ymax>488</ymax>
		</bndbox>
		<contact_state>0,1,0,0,</contact_state>
		<hand_id>5</hand_id>
	</object>

	<object>
		<name>hand</name>
		<pose>Unspecified</pose>
		<truncated>0</truncated>
		<difficult>0</difficult>
		<bndbox>
			<xmin>538</xmin>
			<xmax>583</xmax>
			<ymin>454</ymin>
			<ymax>476</ymax>
		</bndbox>
		<contact_state>0,1,0,0,</contact_state>
		<hand_id>6</hand_id>
	</object>

	<object>
		<name>hand</name>
		<pose>Unspecified</pose>
		<truncated>0</truncated>
		<difficult>0</difficult>
		<bndbox>
			<xmin>679</xmin>
			<xmax>713</xmax>
			<ymin>375</ymin>
			<ymax>398</ymax>
		</bndbox>
		<contact_state>0,1,0,0,</contact_state>
		<hand_id>7</hand_id>
	</object>
</annotation>