<annotation>
	<folder>JPEGImages</folder>
	<filename>train_1412_000000186155.jpg</filename>
	<source>
	<database>Source</database>
	</source>
	<size>
		<width>640</width>
		<height>408</height>
		<depth>3</depth>
	</size>
	<segmented>0</segmented>
	<object>
		<name>hand</name>
		<pose>Unspecified</pose>
		<truncated>0</truncated>
		<difficult>0</difficult>
		<bndbox>
			<xmin>42</xmin>
			<xmax>51</xmax>
			<ymin>65</ymin>
			<ymax>73</ymax>
		</bndbox>
		<contact_state>0,0,0,1,</contact_state>
		<hand_id>1</hand_id>
	</object>

	<object>
		<name>hand</name>
		<pose>Unspecified</pose>
		<truncated>0</truncated>
		<difficult>0</difficult>
		<bndbox>
			<xmin>62</xmin>
			<xmax>71</xmax>
			<ymin>61</ymin>
			<ymax>72</ymax>
		</bndbox>
		<contact_state>0,0,0,1,</contact_state>
		<hand_id>2</hand_id>
	</object>

	<object>
		<name>hand</name>
		<pose>Unspecified</pose>
		<truncated>0</truncated>
		<difficult>0</difficult>
		<bndbox>
			<xmin>224</xmin>
			<xmax>250</xmax>
			<ymin>180</ymin>
			<ymax>201</ymax>
		</bndbox>
		<contact_state>1,0,0,0,</contact_state>
		<hand_id>3</hand_id>
	</object>

	<object>
		<name>hand</name>
		<pose>Unspecified</pose>
		<truncated>0</truncated>
		<difficult>0</difficult>
		<bndbox>
			<xmin>545</xmin>
			<xmax>583</xmax>
			<ymin>146</ymin>
			<ymax>193</ymax>
		</bndbox>
		<contact_state>0,0,0,1,</contact_state>
		<hand_id>4</hand_id>
	</object>

	<object>
		<name>hand</name>
		<pose>Unspecified</pose>
		<truncated>0</truncated>
		<difficult>0</difficult>
		<bndbox>
			<xmin>168</xmin>
			<xmax>180</xmax>
			<ymin>41</ymin>
			<ymax>54</ymax>
		</bndbox>
		<contact_state>1,0,0,0,</contact_state>
		<hand_id>5</hand_id>
	</object>

	<object>
		<name>hand</name>
		<pose>Unspecified</pose>
		<truncated>0</truncated>
		<difficult>0</difficult>
		<bndbox>
			<xmin>125</xmin>
			<xmax>159</xmax>
			<ymin>177</ymin>
			<ymax>201</ymax>
		</bndbox>
		<contact_state>1,0,0,0,</contact_state>
		<hand_id>6</hand_id>
	</object>
</annotation>